check.py
setup.py
Links.egg-info/PKG-INFO
Links.egg-info/SOURCES.txt
Links.egg-info/dependency_links.txt
Links.egg-info/top_level.txt