Metadata-Version: 1.0
Name: Links
Version: 1.0
Summary: Link-utilities missing from urllib|urllib2
Home-page: UNKNOWN
Author: kaleissin
Author-email: kaleissin at gmail com
License: MIT
Platform: UNKNOWN
